imdb/__init__.py
imdb/__main__.py
imdb/api.py
imdb/imdb.py
tdm_lmilewsk-0.1.1.dist-info/LICENCE.txt
tdm_lmilewsk-0.1.1.dist-info/METADATA
tdm_lmilewsk-0.1.1.dist-info/WHEEL
tdm_lmilewsk-0.1.1.dist-info/entry_points.txt
tdm_lmilewsk-0.1.1.dist-info/top_level.txt
tdm_lmilewsk-0.1.1.dist-info/RECORD
